django_multidb_router-0.11.dist-info/licenses/LICENSE
multidb/__init__.py
multidb/middleware.py
multidb/pinning.py
multidb/tests.py
django_multidb_router-0.11.dist-info/METADATA
django_multidb_router-0.11.dist-info/WHEEL
django_multidb_router-0.11.dist-info/top_level.txt
django_multidb_router-0.11.dist-info/RECORD
