Metadata-Version: 2.4
Name: django-multidb-router
Version: 0.11
Summary: Round-robin multidb router for Django.
Home-page: https://github.com/jbalogh/django-multidb-router
Author: Jeff Balogh
Author-email: jbalogh@mozilla.com
License: BSD
Classifier: Development Status :: 4 - Beta
Classifier: Environment :: Web Environment
Classifier: Environment :: Web Environment :: Mozilla
Classifier: Framework :: Django
Classifier: Framework :: Django :: 4.2
Classifier: Framework :: Django :: 5.1
Classifier: Framework :: Django :: 5.2
Classifier: Intended Audience :: Developers
Classifier: License :: OSI Approved :: BSD License
Classifier: Operating System :: OS Independent
Classifier: Programming Language :: Python
Classifier: Programming Language :: Python :: 3
Classifier: Programming Language :: Python :: 3.9
Classifier: Programming Language :: Python :: 3.10
Classifier: Programming Language :: Python :: 3.11
Classifier: Programming Language :: Python :: 3.12
Classifier: Programming Language :: Python :: 3.13
Classifier: Topic :: Software Development :: Libraries :: Python Modules
License-File: LICENSE
Requires-Dist: Django>=4.2
Dynamic: author
Dynamic: author-email
Dynamic: classifier
Dynamic: description
Dynamic: home-page
Dynamic: license
Dynamic: license-file
Dynamic: requires-dist
Dynamic: summary
